upload_to_S3_folder_pkg/__init__.py
upload_to_S3_folder_pkg/upload_to_S3_folder.py
upload_to_s3_folder_pkg-0.0.1.dist-info/LICENCE
upload_to_s3_folder_pkg-0.0.1.dist-info/METADATA
upload_to_s3_folder_pkg-0.0.1.dist-info/WHEEL
upload_to_s3_folder_pkg-0.0.1.dist-info/top_level.txt
upload_to_s3_folder_pkg-0.0.1.dist-info/RECORD
