Metadata-Version: 2.1
Name: upload-to-s3-folder-pkg
Version: 0.0.1
Summary: A small package that will upload your file to a specific S3 folder
Home-page: https://github.com/cormacio100/pypi_upload_to_s3_folder.git
Author: Cormac Liston
Author-email: x21154945@student.ncirl.ie
License: UNKNOWN
Platform: UNKNOWN
Classifier: Programming Language :: Python :: 3
Classifier: License :: OSI Approved :: MIT License
Classifier: Operating System :: OS Independent
Requires-Python: >=3.6
License-File: LICENCE
